claudechic/__init__.py
claudechic/__main__.py
claudechic/agent.py
claudechic/agent_manager.py
claudechic/analytics.py
claudechic/app.py
claudechic/commands.py
claudechic/compact.py
claudechic/config.py
claudechic/context.md
claudechic/enums.py
claudechic/errors.py
claudechic/file_index.py
claudechic/filters.py
claudechic/formatting.py
claudechic/help_data.py
claudechic/history.py
claudechic/mcp.py
claudechic/messages.py
claudechic/permissions.py
claudechic/processes.py
claudechic/profiling.py
claudechic/protocols.py
claudechic/remote.py
claudechic/sampling.py
claudechic/sessions.py
claudechic/shell_complete.py
claudechic/shell_runner.py
claudechic/styles.tcss
claudechic/tasks.py
claudechic/theme.py
claudechic/usage.py
claudechic/features/__init__.py
claudechic/features/diff/__init__.py
claudechic/features/diff/git.py
claudechic/features/diff/widgets.py
claudechic/features/worktree/__init__.py
claudechic/features/worktree/commands.py
claudechic/features/worktree/git.py
claudechic/screens/__init__.py
claudechic/screens/chat.py
claudechic/screens/diff.py
claudechic/screens/session.py
claudechic/widgets/__init__.py
claudechic/widgets/prompts.py
claudechic/widgets/base/__init__.py
claudechic/widgets/base/clickable.py
claudechic/widgets/base/tool_base.py
claudechic/widgets/base/tool_protocol.py
claudechic/widgets/content/__init__.py
claudechic/widgets/content/collapsed_turn.py
claudechic/widgets/content/diff.py
claudechic/widgets/content/message.py
claudechic/widgets/content/todo.py
claudechic/widgets/content/tools.py
claudechic/widgets/input/__init__.py
claudechic/widgets/input/autocomplete.py
claudechic/widgets/input/history_search.py
claudechic/widgets/input/vi_mode.py
claudechic/widgets/layout/__init__.py
claudechic/widgets/layout/chat_view.py
claudechic/widgets/layout/footer.py
claudechic/widgets/layout/indicators.py
claudechic/widgets/layout/processes.py
claudechic/widgets/layout/sidebar.py
claudechic/widgets/modals/__init__.py
claudechic-0.4.12.dist-info/licenses/LICENSE
claudechic-0.4.12.dist-info/METADATA
claudechic-0.4.12.dist-info/WHEEL
claudechic-0.4.12.dist-info/entry_points.txt
claudechic-0.4.12.dist-info/top_level.txt
claudechic-0.4.12.dist-info/RECORD
