Metadata-Version: 2.4
Name: claudechic
Version: 0.4.12
Summary: Claude Chic - A stylish terminal UI for Claude Code
Author-email: Matthew Rocklin <mrocklin@gmail.com>
License-Expression: MIT
Project-URL: Homepage, https://github.com/mrocklin/claudechic
Project-URL: Repository, https://github.com/mrocklin/claudechic
Classifier: Development Status :: 4 - Beta
Classifier: Environment :: Console
Classifier: Intended Audience :: Developers
Classifier: Programming Language :: Python :: 3
Classifier: Programming Language :: Python :: 3.10
Classifier: Programming Language :: Python :: 3.11
Classifier: Programming Language :: Python :: 3.12
Classifier: Programming Language :: Python :: 3.13
Requires-Python: >=3.10
License-File: LICENSE
Requires-Dist: aiofiles>=25.1.0
Requires-Dist: aiohttp>=3.9.0
Requires-Dist: anthropic>=0.75.0
Requires-Dist: claude-agent-sdk<0.1.22,>=0.1.19
Requires-Dist: psutil>=5.9.0
Requires-Dist: pyperclip>=1.11.0
Requires-Dist: pyyaml>=6.0
Requires-Dist: textual>=7.4.0
Requires-Dist: textual-autocomplete>=4.0.6
Dynamic: license-file
